inspirational_quotes/__init__.py
inspirational_quotes/inspirational_quotes.py
inspirational_quotes/quotes.json
inspirational_quotes-0.0.16.dist-info/LICENSE
inspirational_quotes-0.0.16.dist-info/METADATA
inspirational_quotes-0.0.16.dist-info/WHEEL
inspirational_quotes-0.0.16.dist-info/top_level.txt
inspirational_quotes-0.0.16.dist-info/RECORD
