Metadata-Version: 2.1
Name: inspirational_quotes
Version: 0.0.16
Summary: Ideal for developers seeking daily inspiration or anyone looking to add a touch of positivity to their projects. Easily integrate these quotes into your applications, websites, or personal projects to spread motivation and wisdom.
Author-email: saip007 <saip4622@outlook.com>
Keywords: quotes,python,development
Classifier: Programming Language :: Python :: 3
Classifier: License :: OSI Approved :: MIT License
Classifier: Operating System :: OS Independent
Requires-Python: >=3.6
License-File: LICENSE
Requires-Dist: ujson
Provides-Extra: dev
